wakamaro.py
wakamaro-0.0.4.dist-info/METADATA
wakamaro-0.0.4.dist-info/WHEEL
wakamaro-0.0.4.dist-info/entry_points.txt
wakamaro-0.0.4.dist-info/top_level.txt
wakamaro-0.0.4.dist-info/RECORD
