Metadata-Version: 2.1
Name: wakamaro
Version: 0.0.4
Summary: A package for visualizing the number of waka poetry composed by poets in Nijuichidaishu
Home-page: https://github.com/AihaIkegami/wakamaro
Author: aiha ikegami
Author-email: s2022003@stu.musashino-u.ac.jp
License: UNKNOWN
Project-URL: Bug Tracker, https://github.com/AihaIkegami/wakamaro
Platform: UNKNOWN
Classifier: Programming Language :: Python :: 3
Classifier: License :: OSI Approved :: MIT License
Classifier: Operating System :: OS Independent
Requires-Python: >=3.8
